mdfmcp/__init__.py
mdfmcp/server.py
mcp_server_mdf-0.1.3.dist-info/METADATA
mcp_server_mdf-0.1.3.dist-info/WHEEL
mcp_server_mdf-0.1.3.dist-info/entry_points.txt
mcp_server_mdf-0.1.3.dist-info/licenses/LICENSE
mcp_server_mdf-0.1.3.dist-info/licenses/NOTICE
mcp_server_mdf-0.1.3.dist-info/RECORD
