Metadata-Version: 2.4
Name: mcp-server-mdf
Version: 0.1.3
Summary: MCP Server for ASAM MDF file analysis
Project-URL: Homepage, https://github.com/Shanko-26
Project-URL: Repository, https://github.com/Shanko-26/mdfmcp
Project-URL: Issues, https://github.com/Shanko-26/mdfmcp/issues
Author-email: Shanko <shanko_26@yahoo.co.in>
License: MIT
License-File: LICENSE
License-File: NOTICE
Keywords: automotive,data-analysis,mcp,mdf,model-context-protocol
Classifier: Development Status :: 4 - Beta
Classifier: Intended Audience :: Developers
Classifier: License :: OSI Approved :: MIT License
Classifier: Programming Language :: Python :: 3
Classifier: Programming Language :: Python :: 3.10
Classifier: Programming Language :: Python :: 3.11
Classifier: Programming Language :: Python :: 3.12
Classifier: Topic :: Scientific/Engineering :: Information Analysis
Classifier: Topic :: Software Development :: Libraries :: Python Modules
Requires-Python: >=3.10
Requires-Dist: asammdf>=8.0.0
Requires-Dist: matplotlib>=3.6.0
Requires-Dist: mcp[cli]>=1.4.0
Requires-Dist: numpy>=1.24.0
Requires-Dist: pandas>=2.0.0
Provides-Extra: dev
Requires-Dist: black>=22.0.0; extra == 'dev'
Requires-Dist: pytest>=7.0.0; extra == 'dev'
Requires-Dist: ruff>=0.1.0; extra == 'dev'
